setup.py
posort/__init__.py
posort/core.py
posort/util.py
posort.egg-info/PKG-INFO
posort.egg-info/SOURCES.txt
posort.egg-info/dependency_links.txt
posort.egg-info/not-zip-safe
posort.egg-info/top_level.txt