Metadata-Version: 1.0
Name: posort
Version: 0.1
Summary: Partially ordered sort
Home-page: http://github.com/mrocklin/posort
Author: Matthew Rocklin
Author-email: mrocklin@gmail.com
License: BSD
Platform: UNKNOWN
